LICENSE
MANIFEST.in
README.rst
setup.cfg
setup.py
data/MIPAS_atmosphere_profile
data/ParameterFile
data/TAPE5
data/runlblrtm_v3.sh
examples/fit_example/Comparison.pdf
examples/fit_example/Corrected.pdf
examples/fit_example/Fit.py
examples/fit_example/Model.dat
examples/fit_example/README
examples/fit_example/Spectrum.dat
examples/fit_example_fullechelle/Fit.py
examples/fit_example_fullechelle/GDAS_Atmosphere.dat
examples/fit_example_fullechelle/README
examples/fit_example_fullechelle/fitsfile.fits
examples/library_creation/MakeLibrary.py
examples/library_creation/README
examples/library_creation/move_library_here.sh
src/ConvertMIPASto_lblrtm_format.py
src/ConvertMIPASto_lblrtm_format.pyc
src/DataStructures.py
src/DataStructures.pyc
src/FittingUtilities.c
src/FittingUtilities.pyx
src/FittingUtilities.so
src/MakeModel.py
src/MakeModel.pyc
src/MakeTape5.py
src/MakeTape5.pyc
src/TelluricFitter.py
src/TelluricFitter.pyc
src/__init__.pyc
src/TelFit.egg-info/PKG-INFO
src/TelFit.egg-info/SOURCES.txt
src/TelFit.egg-info/dependency_links.txt
src/TelFit.egg-info/requires.txt
src/TelFit.egg-info/top_level.txt
src/telfit/__init__.py
src/telfit/__init__.pyc